LICENSE.txt
MANIFEST.in
README.rst
setup.py
gc_django_redis_sessions.egg-info/PKG-INFO
gc_django_redis_sessions.egg-info/SOURCES.txt
gc_django_redis_sessions.egg-info/dependency_links.txt
gc_django_redis_sessions.egg-info/not-zip-safe
gc_django_redis_sessions.egg-info/pbr.json
gc_django_redis_sessions.egg-info/requires.txt
gc_django_redis_sessions.egg-info/top_level.txt
redis_sessions/__init__.py
redis_sessions/session.py
redis_sessions/settings.py