Metadata-Version: 1.1
Name: gc-django-redis-sessions
Version: 0.5.2
Summary: Redis Session Backend For Django
Home-page: http://github.com/gamechanger/django-redis-sessions
Author: Martin Rusev
Author-email: martinrusev@live.com
License: BSD
Keywords: django,sessions,
Platform: UNKNOWN
Classifier: Programming Language :: Python :: 2
Classifier: Programming Language :: Python :: 3
Classifier: Topic :: Software Development :: Libraries :: Python Modules
Classifier: Framework :: Django
Classifier: Environment :: Web Environment
